ANIBBLE_X/__init__.py
ANIBBLE_X/graph_show.py
ANIBBLE_X/graph_visualisation_toolskit.py
ANIBBLE_X-0.7.22.data/data/data_VIS/vis.css
ANIBBLE_X-0.7.22.data/data/data_VIS/vis.js
ANIBBLE_X-0.7.22.dist-info/LICENSE
ANIBBLE_X-0.7.22.dist-info/METADATA
ANIBBLE_X-0.7.22.dist-info/WHEEL
ANIBBLE_X-0.7.22.dist-info/top_level.txt
ANIBBLE_X-0.7.22.dist-info/RECORD
