Metadata-Version: 2.1
Name: ANIBBLE-X
Version: 0.7.22
Summary: Creation of html graph from networkx
Home-page: UNKNOWN
Author: Mélanie Sawaryn
Author-email: melanie.sawaryn@gmail.com
License: UNKNOWN
Platform: UNKNOWN
Classifier: Programming Language :: Python
Classifier: Programming Language :: Python :: 3
Classifier: Programming Language :: Python :: 3.6
